ml_lib/__init__.py
ml_lib/core.py
custom_pandas-0.1.0.dist-info/METADATA
custom_pandas-0.1.0.dist-info/WHEEL
custom_pandas-0.1.0.dist-info/top_level.txt
custom_pandas-0.1.0.dist-info/RECORD
